[{"id":1,"title":"Black Book (Zwartboek)","author":"Amandy Castellanos","year":1979},
{"id":2,"title":"Silent Movie","author":"Bobby Heater","year":1970},
{"id":3,"title":"Everyone's Hero","author":"Elnora Rookledge","year":1988},
{"id":4,"title":"New Gladiators (I guerrieri dell'anno 2072)","author":"Franky Marousek","year":1977},
{"id":5,"title":"Quatre garçons pleins d'avenir","author":"Alleen Scanes","year":1953},
{"id":6,"title":"Down to the Bone","author":"Flossy Fosher","year":1997},
{"id":7,"title":"Trouble in Paradise","author":"Cass Kingsworth","year":1956},
{"id":8,"title":"Ghetto (Vilniaus Getas)","author":"Brande Brine","year":1955},
{"id":9,"title":"Happy Together (a.k.a. Buenos Aires Affair) (Chun gwong cha sit)","author":"Armando Yitzhakof","year":1949},
{"id":10,"title":"Night Falls on Manhattan","author":"Haskel Axtens","year":1966},
{"id":11,"title":"Kiss, The","author":"Zachary Splevin","year":1954},
{"id":12,"title":"According to Spencer","author":"Esra Cordel","year":1956},
{"id":13,"title":"Cincinnati Kid, The","author":"Alwin Pargent","year":1983},
{"id":14,"title":"Tyler Perry's The Single Moms Club","author":"Frants Kleinholz","year":1977},
{"id":15,"title":"Half Light","author":"Pernell Vasyukhnov","year":1987},
{"id":16,"title":"Garbage Pail Kids Movie, The","author":"Papageno Geeraert","year":1976},
{"id":17,"title":"Gift, The","author":"Shanna Iggo","year":1947},
{"id":18,"title":"Corridors of Time: The Visitors II, The (Couloirs du temps: Les visiteurs 2, Les)","author":"Jaquenette MacMeanma","year":1973},
{"id":19,"title":"Night of the Running Man","author":"Rosalind Kilgrove","year":1998},
{"id":20,"title":"Home Alone 2: Lost in New York","author":"Bili Petrol","year":1960},
{"id":21,"title":"Hitch-Hiker, The","author":"Georgy Linstead","year":1985},
{"id":22,"title":"L.A. Confidential","author":"Had Rein","year":1978},
{"id":23,"title":"Finding Fela!","author":"Pieter Tomasutti","year":1956},
{"id":24,"title":"Something New","author":"Rolland Winskill","year":1965},
{"id":25,"title":"Days of Glory (Indigènes)","author":"Angelia Pirazzi","year":1997},
{"id":26,"title":"Two if by Sea","author":"Oralle Mabb","year":1973},
{"id":27,"title":"Village People Radio Show (Apa khabar orang kampung)","author":"Glen Covolini","year":1995},
{"id":28,"title":"Happiest Millionaire, The","author":"Julina Chasmor","year":1977},
{"id":29,"title":"Summer Lovers","author":"Mariellen Duchenne","year":1948},
{"id":30,"title":"Thirty-Five Something (Tout pour plaire)","author":"Florie Wright","year":1953},
{"id":31,"title":"Rejs","author":"Shaughn Barnwall","year":1986},
{"id":32,"title":"Lady Takes a Chance, A","author":"Ilyse Reilly","year":1983},
{"id":33,"title":"Dobermann","author":"Brunhilda Denes","year":1974},
{"id":34,"title":"Pagemaster, The","author":"Melisenda Stuttman","year":1996},
{"id":35,"title":"Ice Cream Man","author":"Darleen Andreoletti","year":1994},
{"id":36,"title":"Descent: Part 2, The","author":"Xenos Mundford","year":1981},
{"id":37,"title":"The Stoker","author":"Herve Matiashvili","year":1981},
{"id":38,"title":"Mob, The","author":"Peyton Moyce","year":1961},
{"id":39,"title":"Beyond the Valley of the Dolls","author":"Blondell Messer","year":1985},
{"id":40,"title":"Beauty and the Beast","author":"Editha Parsand","year":1981},
{"id":41,"title":"Goodbye, Dragon Inn (Bu san)","author":"Zeb Gainsford","year":1982},
{"id":42,"title":"Amos & Andrew","author":"Parke Stivens","year":1987},
{"id":43,"title":"The Facts of Murder","author":"Chere Hanham","year":1958},
{"id":44,"title":"From Beyond the Grave (Creatures)","author":"Cherish Planque","year":1955},
{"id":45,"title":"Occupant","author":"Jackson Haddacks","year":1998},
{"id":46,"title":"Two Queens and One Consort (Twee vorstinnen en een vorst)","author":"Trenton Fumagallo","year":1952},
{"id":47,"title":"Love Me If You Dare (Jeux d'enfants)","author":"Eran Veeler","year":1961},
{"id":48,"title":"Nina Frisk","author":"Ame McShirie","year":1960},
{"id":49,"title":"My Chauffeur","author":"Yettie Sinderson","year":1998},
{"id":50,"title":"Kingdom, The (Riget)","author":"Bryant Ambrosetti","year":1989}]